tkintermessenger/__init__.py
tkintermessenger/__main__.py
tkintermessenger/netw.py
tkintermessenger/rsa.py
tkintermessenger/messengerUI/__init__.py
tkintermessenger/messengerUI/sound.wav
tkintermessenger/messengerUI/widgets.py
tkintermessenger-0.0.9.dist-info/LICENSE
tkintermessenger-0.0.9.dist-info/METADATA
tkintermessenger-0.0.9.dist-info/WHEEL
tkintermessenger-0.0.9.dist-info/top_level.txt
tkintermessenger-0.0.9.dist-info/RECORD
