Metadata-Version: 2.1
Name: tkintermessenger
Version: 0.0.9
Summary: A messenger written in Python
Home-page: https://github.com/thunfisch987/pythonmessenger
Author: Oliver Sader
Author-email: thunfisch987@gmail.com
License: UNKNOWN
Project-URL: Bug Tracker, https://github.com/thunfisch987/pythonmessenger/issues
Keywords: messenger,network,GUI,tkinter
Platform: UNKNOWN
Classifier: Programming Language :: Python :: 3
Classifier: License :: OSI Approved :: MIT License
Classifier: Operating System :: OS Independent
Requires-Python: >=3
License-File: LICENSE
Requires-Dist: dataclasses
Requires-Dist: playsound (==1.2.2)
Requires-Dist: IPy
